MANIFEST.in
README.rst
setup.py
closure_soy/__init__.py
closure_soy/soy.jar
closure_soy.egg-info/PKG-INFO
closure_soy.egg-info/SOURCES.txt
closure_soy.egg-info/dependency_links.txt
closure_soy.egg-info/entry_points.txt
closure_soy.egg-info/not-zip-safe
closure_soy.egg-info/top_level.txt