Metadata-Version: 1.1
Name: closure-soy
Version: 20121221
Summary: Google Closure's Soy templates packaged for Python
Home-page: http://pypi.python.org/pypi/closure-soy
Author: Michael Su
Author-email: mdasu1@gmail.com
License: BSD
Platform: UNKNOWN
Classifier: Development Status :: 5 - Production/Stable
Classifier: Environment :: Web Environment
Classifier: License :: OSI Approved :: BSD License
Classifier: Topic :: Internet :: WWW/HTTP :: Site Management
